<xml xmlns:o="urn:schemas-microsoft-com:office:office">
 <o:File HRef="v3_document.html"/>
 <o:File HRef="preview.wmf"/>
 <o:File HRef="v3_next_active.gif"/>
 <o:File HRef="v3_next_disabled.gif"/>
 <o:File HRef="v3_prev_active.gif"/>
 <o:File HRef="v3_prev_disabled.gif"/>
 <o:File HRef="v3_outline_collapse.gif"/>
 <o:File HRef="v3_outline_expand.gif"/>
 <o:File HRef="v3_space.gif"/>
 <o:File HRef="v3_endshow.html"/>
 <o:File HRef="v3_navigation_bar.html"/>
 <o:File HRef="v3_outline_navigation_bar.html"/>
 <o:File HRef="v3_outline_collapsed.html"/>
 <o:File HRef="v3_outline_expanded.html"/>
 <o:File HRef="v3_blank_notes.html"/>
 <o:File HRef="master28.html"/>
 <o:File HRef="master28.xml"/>
 <o:File HRef="master29.html"/>
 <o:File HRef="master29.xml"/>
 <o:File HRef="pres.xml"/>
 <o:File HRef="v3_slide0001.html"/>
 <o:File HRef="v3_master29_background.gif"/>
 <o:File HRef="v3_slide0002.html"/>
 <o:File HRef="v3_master28_background.gif"/>
 <o:File HRef="v3_master28_image001.gif"/>
 <o:File HRef="v3_master28_image002.gif"/>
 <o:File HRef="v3_master28_image003.gif"/>
 <o:File HRef="v3_slide0003.html"/>
 <o:File HRef="v3_slide0003_image004.jpg"/>
 <o:File HRef="v3_master28_image005.gif"/>
 <o:File HRef="v3_master28_image006.gif"/>
 <o:File HRef="v3_master28_image007.gif"/>
 <o:File HRef="v3_slide0008.html"/>
 <o:File HRef="v3_slide0008_background.gif"/>
 <o:File HRef="v3_slide0008_image008.jpg"/>
 <o:File HRef="v3_master28_image009.gif"/>
 <o:File HRef="v3_master28_image010.gif"/>
 <o:File HRef="v3_slide0030.html"/>
 <o:File HRef="v3_slide0030_background.gif"/>
 <o:File HRef="v3_slide0030_image011.gif"/>
 <o:File HRef="v3_slide0030_image012.gif"/>
 <o:File HRef="v3_master28_image013.gif"/>
 <o:File HRef="v3_master28_image014.gif"/>
 <o:File HRef="v3_master28_image015.gif"/>
 <o:File HRef="v3_slide0022.html"/>
 <o:File HRef="v3_slide0022_background.gif"/>
 <o:File HRef="v3_master28_image016.gif"/>
 <o:File HRef="v3_master28_image017.gif"/>
 <o:File HRef="v3_master28_image018.gif"/>
 <o:File HRef="v3_slide0043.html"/>
 <o:File HRef="v3_slide0043_image019.jpg"/>
 <o:File HRef="v3_master28_image020.gif"/>
 <o:File HRef="v3_master28_image021.gif"/>
 <o:File HRef="v3_master28_image022.gif"/>
 <o:File HRef="v3_slide0025.html"/>
 <o:File HRef="v3_slide0025_image023.jpg"/>
 <o:File HRef="v3_master28_image024.gif"/>
 <o:File HRef="v3_master28_image025.gif"/>
 <o:File HRef="v3_master28_image026.gif"/>
 <o:File HRef="v3_slide0028.html"/>
 <o:File HRef="v3_slide0028_image027.gif"/>
 <o:File HRef="v3_slide0028_image028.jpg"/>
 <o:File HRef="v3_master28_image029.gif"/>
 <o:File HRef="v3_master28_image030.gif"/>
 <o:File HRef="v3_master28_image031.gif"/>
 <o:File HRef="v3_slide0026.html"/>
 <o:File HRef="v3_slide0026_image032.jpg"/>
 <o:File HRef="v3_master28_image033.gif"/>
 <o:File HRef="v3_master28_image034.gif"/>
 <o:File HRef="v3_master28_image035.gif"/>
 <o:File HRef="v3_slide0027.html"/>
 <o:File HRef="v3_slide0027_image036.gif"/>
 <o:File HRef="v3_master28_image037.gif"/>
 <o:File HRef="v3_master28_image038.gif"/>
 <o:File HRef="v3_master28_image039.gif"/>
 <o:File HRef="v3_slide0059.html"/>
 <o:File HRef="v3_slide0059_image040.gif"/>
 <o:File HRef="v3_master28_image041.gif"/>
 <o:File HRef="v3_master28_image042.gif"/>
 <o:File HRef="v3_master28_image043.gif"/>
 <o:File HRef="v3_slide0071.html"/>
 <o:File HRef="v3_slide0071_image044.gif"/>
 <o:File HRef="v3_master28_image045.gif"/>
 <o:File HRef="v3_master28_image046.gif"/>
 <o:File HRef="v3_master28_image047.gif"/>
 <o:File HRef="v3_slide0074.html"/>
 <o:File HRef="v3_slide0074_background.gif"/>
 <o:File HRef="v3_slide0074_image048.gif"/>
 <o:File HRef="v3_slide0074_image049.gif"/>
 <o:File HRef="v3_slide0074_image050.gif"/>
 <o:File HRef="v3_slide0074_image051.gif"/>
 <o:File HRef="v3_slide0074_image052.gif"/>
 <o:File HRef="v3_master28_image053.gif"/>
 <o:File HRef="v3_master28_image054.gif"/>
 <o:File HRef="v3_master28_image055.gif"/>
 <o:File HRef="v3_slide0009.html"/>
 <o:File HRef="v3_slide0009_image056.gif"/>
 <o:File HRef="v3_master28_image057.gif"/>
 <o:File HRef="v3_master28_image058.gif"/>
 <o:File HRef="v3_master28_image059.gif"/>
 <o:File HRef="v3_slide0032.html"/>
 <o:File HRef="v3_master28_image060.gif"/>
 <o:File HRef="v3_master28_image061.gif"/>
 <o:File HRef="v3_master28_image062.gif"/>
 <o:File HRef="v3_slide0033.html"/>
 <o:File HRef="v3_slide0033_image063.gif"/>
 <o:File HRef="v3_master28_image064.gif"/>
 <o:File HRef="v3_master28_image065.gif"/>
 <o:File HRef="v3_master28_image066.gif"/>
 <o:File HRef="v3_slide0034.html"/>
 <o:File HRef="v3_master28_image067.gif"/>
 <o:File HRef="v3_master28_image068.gif"/>
 <o:File HRef="v3_master28_image069.gif"/>
 <o:File HRef="v3_slide0040.html"/>
 <o:File HRef="v3_master28_image070.jpg"/>
 <o:File HRef="v3_slide0042.html"/>
 <o:File HRef="v3_master28_image071.gif"/>
 <o:File HRef="v3_slide0035.html"/>
 <o:File HRef="v3_slide0035_image072.gif"/>
 <o:File HRef="v3_master28_image073.gif"/>
 <o:File HRef="v3_master28_image074.gif"/>
 <o:File HRef="v3_master28_image075.gif"/>
 <o:File HRef="v3_slide0036.html"/>
 <o:File HRef="v3_master28_image076.gif"/>
 <o:File HRef="v3_master28_image077.gif"/>
 <o:File HRef="v3_master28_image078.gif"/>
 <o:File HRef="v3_slide0011.html"/>
 <o:File HRef="v3_master28_image079.gif"/>
 <o:File HRef="v3_master28_image080.gif"/>
 <o:File HRef="v3_master28_image081.gif"/>
 <o:File HRef="v3_slide0077.html"/>
 <o:File HRef="v3_master28_image082.gif"/>
 <o:File HRef="v3_master28_image083.gif"/>
 <o:File HRef="v3_master28_image084.gif"/>
 <o:File HRef="v3_slide0066.html"/>
 <o:File HRef="v3_master28_image085.gif"/>
 <o:File HRef="v3_master28_image086.gif"/>
 <o:File HRef="v3_master28_image087.gif"/>
 <o:File HRef="v3_slide0060.html"/>
 <o:File HRef="v3_slide0060_image088.gif"/>
 <o:File HRef="v3_master28_image089.gif"/>
 <o:File HRef="v3_master28_image090.gif"/>
 <o:File HRef="v3_master28_image091.gif"/>
 <o:File HRef="v3_slide0068.html"/>
 <o:File HRef="v3_master28_image092.gif"/>
 <o:File HRef="v3_master28_image093.gif"/>
 <o:File HRef="v3_master28_image094.gif"/>
 <o:File HRef="v3_slide0062.html"/>
 <o:File HRef="v3_slide0062_background.gif"/>
 <o:File HRef="v3_master28_image095.gif"/>
 <o:File HRef="v3_master28_image096.gif"/>
 <o:File HRef="v3_slide0046.html"/>
 <o:File HRef="v3_master28_image097.gif"/>
 <o:File HRef="v3_master28_image098.gif"/>
 <o:File HRef="v3_master28_image099.gif"/>
 <o:File HRef="v3_slide0069.html"/>
 <o:File HRef="v3_slide0069_image100.jpg"/>
 <o:File HRef="v3_master28_image101.gif"/>
 <o:File HRef="v3_master28_image102.gif"/>
 <o:File HRef="v3_master28_image103.gif"/>
 <o:File HRef="v3_slide0047.html"/>
 <o:File HRef="v3_master28_image104.gif"/>
 <o:File HRef="v3_master28_image105.gif"/>
 <o:File HRef="v3_master28_image106.gif"/>
 <o:File HRef="v3_slide0061.html"/>
 <o:File HRef="v3_slide0061_image107.jpg"/>
 <o:File HRef="v3_master28_image108.gif"/>
 <o:File HRef="v3_master28_image109.gif"/>
 <o:File HRef="v3_master28_image110.gif"/>
 <o:File HRef="v3_slide0048.html"/>
 <o:File HRef="v3_slide0048_image111.gif"/>
 <o:File HRef="v3_master28_image112.gif"/>
 <o:File HRef="v3_master28_image113.gif"/>
 <o:File HRef="v3_master28_image114.gif"/>
 <o:File HRef="v3_slide0049.html"/>
 <o:File HRef="v3_slide0049_background.gif"/>
 <o:File HRef="v3_master28_image115.gif"/>
 <o:File HRef="v3_master28_image116.gif"/>
 <o:File HRef="v3_master28_image117.gif"/>
 <o:File HRef="v3_slide0050.html"/>
 <o:File HRef="v3_slide0050_background.gif"/>
 <o:File HRef="v3_master28_image118.gif"/>
 <o:File HRef="v3_master28_image119.gif"/>
 <o:File HRef="v3_master28_image120.gif"/>
 <o:File HRef="v3_slide0072.html"/>
 <o:File HRef="v3_master28_image121.gif"/>
 <o:File HRef="v3_master28_image122.gif"/>
 <o:File HRef="v3_master28_image123.gif"/>
 <o:File HRef="v3_slide0075.html"/>
 <o:File HRef="v3_master28_image124.gif"/>
 <o:File HRef="v3_master28_image125.gif"/>
 <o:File HRef="v3_master28_image126.gif"/>
 <o:File HRef="v3_slide0076.html"/>
 <o:File HRef="v3_master28_image127.gif"/>
 <o:File HRef="v3_master28_image128.gif"/>
 <o:File HRef="v3_master28_image129.gif"/>
 <o:File HRef="v3_slide0056.html"/>
 <o:File HRef="v3_master28_image130.gif"/>
 <o:File HRef="v3_master28_image131.gif"/>
 <o:File HRef="v3_master28_image132.gif"/>
 <o:File HRef="v3_slide0055.html"/>
 <o:File HRef="v3_slide0055_image133.gif"/>
 <o:File HRef="v3_slide0055_image134.jpg"/>
 <o:File HRef="v3_master28_image135.gif"/>
 <o:File HRef="v3_master28_image136.gif"/>
 <o:File HRef="v3_master28_image137.gif"/>
 <o:File HRef="v3_slide0057.html"/>
 <o:File HRef="v3_master28_image138.gif"/>
 <o:File HRef="v3_master28_image139.gif"/>
 <o:File HRef="v3_master28_image140.gif"/>
 <o:File HRef="v3_slide0039.html"/>
 <o:File HRef="v3_master28_image141.gif"/>
 <o:File HRef="v3_master28_image142.gif"/>
 <o:File HRef="v3_master28_image143.gif"/>
 <o:File HRef="v3_slide0053.html"/>
 <o:File HRef="v3_slide0053_image144.gif"/>
 <o:File HRef="v3_slide0053_image145.gif"/>
 <o:File HRef="v3_master28_image146.gif"/>
 <o:File HRef="v3_master28_image147.gif"/>
 <o:File HRef="v3_master28_image148.gif"/>
 <o:File HRef="v3_slide0078.html"/>
 <o:File HRef="v3_master28_image149.gif"/>
 <o:File HRef="v3_master28_image150.gif"/>
 <o:File HRef="v3_master28_image151.gif"/>
 <o:File HRef="slide0001.html"/>
 <o:File HRef="master29_background.gif"/>
 <o:File HRef="master29_image152.gif"/>
 <o:File HRef="slide0002.html"/>
 <o:File HRef="master28_background.gif"/>
 <o:File HRef="master28_image153.gif"/>
 <o:File HRef="slide0003.html"/>
 <o:File HRef="slide0003_image154.jpg"/>
 <o:File HRef="slide0003_image155.jpg"/>
 <o:File HRef="slide0008.html"/>
 <o:File HRef="slide0008_image156.jpg"/>
 <o:File HRef="slide0008_image157.jpg"/>
 <o:File HRef="slide0030.html"/>
 <o:File HRef="slide0030_image158.gif"/>
 <o:File HRef="slide0030_image159.gif"/>
 <o:File HRef="slide0030_image160.gif"/>
 <o:File HRef="slide0030_image161.gif"/>
 <o:File HRef="slide0030_image162.gif"/>
 <o:File HRef="slide0022.html"/>
 <o:File HRef="slide0043.html"/>
 <o:File HRef="slide0043_image163.jpg"/>
 <o:File HRef="slide0043_image164.jpg"/>
 <o:File HRef="slide0025.html"/>
 <o:File HRef="slide0025_image165.jpg"/>
 <o:File HRef="slide0025_image166.jpg"/>
 <o:File HRef="slide0028.html"/>
 <o:File HRef="slide0028_image167.jpg"/>
 <o:File HRef="slide0028_image168.jpg"/>
 <o:File HRef="slide0026.html"/>
 <o:File HRef="slide0026_image169.jpg"/>
 <o:File HRef="slide0026_image170.jpg"/>
 <o:File HRef="slide0027.html"/>
 <o:File HRef="slide0059.html"/>
 <o:File HRef="slide0071.html"/>
 <o:File HRef="slide0074.html"/>
 <o:File HRef="slide0074_image171.gif"/>
 <o:File HRef="slide0074_image172.gif"/>
 <o:File HRef="slide0074_image173.gif"/>
 <o:File HRef="slide0074_image174.gif"/>
 <o:File HRef="slide0074_image175.gif"/>
 <o:File HRef="slide0074_image176.gif"/>
 <o:File HRef="slide0074_image177.gif"/>
 <o:File HRef="slide0009.html"/>
 <o:File HRef="slide0032.html"/>
 <o:File HRef="slide0033.html"/>
 <o:File HRef="slide0034.html"/>
 <o:File HRef="slide0040.html"/>
 <o:File HRef="slide0040_image178.png"/>
 <o:File HRef="slide0040_image179.jpg"/>
 <o:File HRef="slide0042.html"/>
 <o:File HRef="slide0042_image180.wmz"/>
 <o:File HRef="oledata.mso"/>
 <o:File HRef="slide0042_image181.gif"/>
 <o:File HRef="slide0035.html"/>
 <o:File HRef="slide0036.html"/>
 <o:File HRef="slide0011.html"/>
 <o:File HRef="slide0077.html"/>
 <o:File HRef="slide0066.html"/>
 <o:File HRef="slide0060.html"/>
 <o:File HRef="slide0060_image182.jpg"/>
 <o:File HRef="slide0060_image183.jpg"/>
 <o:File HRef="slide0068.html"/>
 <o:File HRef="slide0062.html"/>
 <o:File HRef="slide0062_image184.jpg"/>
 <o:File HRef="slide0062_image185.jpg"/>
 <o:File HRef="slide0046.html"/>
 <o:File HRef="slide0046_image186.jpg"/>
 <o:File HRef="slide0046_image187.jpg"/>
 <o:File HRef="slide0069.html"/>
 <o:File HRef="slide0069_image188.jpg"/>
 <o:File HRef="slide0069_image189.jpg"/>
 <o:File HRef="slide0047.html"/>
 <o:File HRef="slide0061.html"/>
 <o:File HRef="slide0061_image190.jpg"/>
 <o:File HRef="slide0061_image191.jpg"/>
 <o:File HRef="slide0048.html"/>
 <o:File HRef="slide0049.html"/>
 <o:File HRef="slide0049_image192.gif"/>
 <o:File HRef="slide0049_image193.gif"/>
 <o:File HRef="slide0050.html"/>
 <o:File HRef="slide0050_image194.jpg"/>
 <o:File HRef="slide0050_image195.jpg"/>
 <o:File HRef="slide0072.html"/>
 <o:File HRef="slide0075.html"/>
 <o:File HRef="slide0076.html"/>
 <o:File HRef="slide0056.html"/>
 <o:File HRef="slide0055.html"/>
 <o:File HRef="slide0055_image196.jpg"/>
 <o:File HRef="slide0055_image197.jpg"/>
 <o:File HRef="slide0057.html"/>
 <o:File HRef="slide0039.html"/>
 <o:File HRef="slide0053.html"/>
 <o:File HRef="slide0078.html"/>
 <o:File HRef="master01.html"/>
 <o:File HRef="master28_stylesheet.css"/>
 <o:File HRef="script.js"/>
 <o:MainFile HRef="../index.html"/>
 <o:File HRef="fullscreen.html"/>
 <o:File HRef="buttons.gif"/>
 <o:File HRef="frame.html"/>
 <o:File HRef="outline.html"/>
 <o:File HRef="filelist.xml"/>
</xml>